{
  "name": "Phantom",
  "description": "Join The Phantom Thieves of Hearts with this theme that stylizes your recent games and library to look like the UI from Persona 5.",
  "author": "EMERALD#0874",
  "target": "System-Wide",
  "version": "v1.0",
  "inject": {
    "shared.css": ["SP"]
  },
  "patches": {
    "Installation": {
      "default": "All",
      "All": { "colors.css": ["SP"] },
      "Minimal": {}
    },
    "Flat": {
      "default": "Yes",
      "Yes": { "flat.css": ["SP"] },
      "No": {}
    }
  }
}
